EffectiveCpp/README.md
EffectiveCpp/__init__.py
EffectiveCpp/__main__.py
EffectiveCpp/file.epub
EffectiveCpp/index.html
EffectiveCpp/css/__init__.py
EffectiveCpp/css/annotations.css
EffectiveCpp/css/main.css
EffectiveCpp/css/normalize.css
EffectiveCpp/css/popup.css
EffectiveCpp/font/__init__.py
EffectiveCpp/font/fontello.eot
EffectiveCpp/font/fontello.svg
EffectiveCpp/font/fontello.ttf
EffectiveCpp/font/fontello.woff
EffectiveCpp/img/__init__.py
EffectiveCpp/img/annotator-glyph-sprite.png
EffectiveCpp/img/annotator-icon-sprite.png
EffectiveCpp/img/apple-touch-icon.png
EffectiveCpp/img/cancelfullscreen.png
EffectiveCpp/img/close.png
EffectiveCpp/img/fullscreen.png
EffectiveCpp/img/loader.gif
EffectiveCpp/img/menu-icon.png
EffectiveCpp/img/save.png
EffectiveCpp/img/saved.png
EffectiveCpp/img/settings-s.png
EffectiveCpp/img/settings.png
EffectiveCpp/img/star.png
EffectiveCpp/js/__init__.py
EffectiveCpp/js/epub.js
EffectiveCpp/js/epub.min.js
EffectiveCpp/js/epub.min.map
EffectiveCpp/js/hooks.min.js
EffectiveCpp/js/hooks.min.map
EffectiveCpp/js/reader.js
EffectiveCpp/js/reader.js.map
EffectiveCpp/js/reader.min.js
EffectiveCpp/js/reader.min.map
EffectiveCpp/js/hooks/__init__.py
EffectiveCpp/js/hooks/extensions/__init__.py
EffectiveCpp/js/hooks/extensions/highlight.js
EffectiveCpp/js/libs/__init__.py
EffectiveCpp/js/libs/jquery.min.js
EffectiveCpp/js/libs/localforage.min.js
EffectiveCpp/js/libs/screenfull.js
EffectiveCpp/js/libs/screenfull.min.js
EffectiveCpp/js/libs/zip.min.js
EffectiveCpp/js/plugins/__init__.py
EffectiveCpp/js/plugins/hypothesis.js
EffectiveCpp/js/plugins/search.js
effective_cpp-2024.3.1.0.dist-info/METADATA
effective_cpp-2024.3.1.0.dist-info/WHEEL
effective_cpp-2024.3.1.0.dist-info/entry_points.txt
effective_cpp-2024.3.1.0.dist-info/top_level.txt
effective_cpp-2024.3.1.0.dist-info/RECORD
